steadysun/__init__.py
steadysun/_api.py
steadysun/forecast.py
steadysun/pvsystem.py
steadysun/steadysun_api.py
steadysun/models/_utils.py
steadysun/models/pvsystem.py
steadysun-0.1.0.dist-info/LICENSE
steadysun-0.1.0.dist-info/METADATA
steadysun-0.1.0.dist-info/WHEEL
steadysun-0.1.0.dist-info/top_level.txt
steadysun-0.1.0.dist-info/RECORD
