Metadata-Version: 2.1
Name: steadysun
Version: 0.1.0
Summary: A package to interact with Steadysun's API
Author-email: Pierrick MADE <pierrick.made@steady-sun.com>
License: MIT License
Project-URL: Homepage, https://www.steady-sun.com
Project-URL: Documentation, https://steadysun-pypi.readthedocs.io
Project-URL: Repository, https://github.com/steadysun-pmade/steadysun-pypi/issues
Project-URL: Issues, https://github.com/steadysun-pmade/steadysun-pypi/issues
Project-URL: Changelog, https://github.com/steadysun-pmade/steadysun-pypi/blob/master/CHANGELOG.md
Classifier: Programming Language :: Python :: 3
Classifier: License :: OSI Approved :: MIT License
Classifier: Operating System :: OS Independent
Requires-Python: >=3.8
License-File: LICENSE
Requires-Dist: geojson
Requires-Dist: pandas
Requires-Dist: pydantic
Requires-Dist: pydantic-geojson
Requires-Dist: requests
